Tami4EdgeAPI/Tami4EdgeAPI.py
Tami4EdgeAPI/__init__.py
Tami4EdgeAPI/device.py
Tami4EdgeAPI/drink.py
Tami4EdgeAPI/exceptions.py
Tami4EdgeAPI/token.py
Tami4EdgeAPI/water_quality.py
Tami4EdgeAPI-2.1.dist-info/LICENSE
Tami4EdgeAPI-2.1.dist-info/METADATA
Tami4EdgeAPI-2.1.dist-info/WHEEL
Tami4EdgeAPI-2.1.dist-info/top_level.txt
Tami4EdgeAPI-2.1.dist-info/RECORD
