Metadata-Version: 2.1
Name: Tami4EdgeAPI
Version: 2.1
Home-page: https://github.com/Guy293/Tami4EdgeAPI
Author: Guy Shefer
License: MIT
License-File: LICENSE
Requires-Dist: requests
Requires-Dist: pypasser
